{
    "version": "5.4.1",
    "flags": {},
    "shapes": [
        {
            "label": "1",
            "points": [
                [
                    181.0476190476191,
                    656.047619047619
                ],
                [
                    32.23809523809524,
                    491.76190476190476
                ]
            ],
            "group_id": null,
            "description": "",
            "shape_type": "rectangle",
            "flags": {},
            "mask": null
        },
        {
            "label": "1",
            "points": [
                [
                    60.809523809523796,
                    947.7142857142858
                ],
                [
                    0.0,
                    806.479262672811
                ]
            ],
            "group_id": null,
            "description": "",
            "shape_type": "rectangle",
            "flags": {},
            "mask": null
        },
        {
            "label": "1",
            "points": [
                [
                    257.83333333333337,
                    370.3333333333333
                ],
                [
                    534.6190476190477,
                    641.7619047619048
                ]
            ],
            "group_id": null,
            "description": "",
            "shape_type": "rectangle",
            "flags": {},
            "mask": null
        },
        {
            "label": "1",
            "points": [
                [
                    871.5238095238094,
                    147.71428571428572
                ],
                [
                    1022.7832380952382,
                    0.0
                ]
            ],
            "group_id": null,
            "description": "",
            "shape_type": "rectangle",
            "flags": {},
            "mask": null
        },
        {
            "label": "1",
            "points": [
                [
                    325.69047619047615,
                    289.3809523809524
                ],
                [
                    453.07142857142856,
                    379.8571428571429
                ]
            ],
            "group_id": null,
            "description": "",
            "shape_type": "rectangle",
            "flags": {},
            "mask": null
        }
    ],
    "imageHeight": 1024,
    "imageWidth": 1024
}