{
    "version": "5.4.1",
    "flags": {},
    "shapes": [
        {
            "label": "1",
            "points": [
                [
                    376.2857142857143,
                    170.33333333333334
                ],
                [
                    123.90476190476193,
                    3.666666666666648
                ]
            ],
            "group_id": null,
            "description": "",
            "shape_type": "rectangle",
            "flags": {},
            "mask": null
        },
        {
            "label": "1",
            "points": [
                [
                    669.7380952380952,
                    620.3333333333334
                ],
                [
                    773.3095238095237,
                    794.1428571428571
                ]
            ],
            "group_id": null,
            "description": "",
            "shape_type": "rectangle",
            "flags": {},
            "mask": null
        },
        {
            "label": "1",
            "points": [
                [
                    598.3095238095239,
                    457.23809523809524
                ],
                [
                    701.8809523809524,
                    607.2380952380953
                ]
            ],
            "group_id": null,
            "description": "",
            "shape_type": "rectangle",
            "flags": {},
            "mask": null
        }
    ],
    "imageHeight": 1024,
    "imageWidth": 1024
}