{
    "version": "5.4.1",
    "flags": {},
    "shapes": [
        {
            "label": "1",
            "points": [
                [
                    459.0238095238095,
                    421.5238095238095
                ],
                [
                    534.0238095238095,
                    502.4761904761905
                ]
            ],
            "group_id": null,
            "description": "",
            "shape_type": "rectangle",
            "flags": {},
            "mask": null
        }
    ],
    "imageHeight": 1024,
    "imageWidth": 1024
}