{
    "version": "5.4.1",
    "flags": {},
    "shapes": [
        {
            "label": "1",
            "points": [
                [
                    175.31168831168821,
                    401.77272727272725
                ],
                [
                    297.1190476190476,
                    539.3809523809524
                ]
            ],
            "group_id": null,
            "description": "",
            "shape_type": "rectangle",
            "flags": {},
            "mask": null
        },
        {
            "label": "1",
            "points": [
                [
                    399.5,
                    832.2380952380953
                ],
                [
                    129.26190476190476,
                    976.2857142857143
                ]
            ],
            "group_id": null,
            "description": "",
            "shape_type": "rectangle",
            "flags": {},
            "mask": null
        }
    ],
    "imageHeight": 1024,
    "imageWidth": 1024
}