{
    "version": "5.4.1",
    "flags": {},
    "shapes": [
        {
            "label": "1",
            "points": [
                [
                    355.1818181818182,
                    244.95454545454547
                ],
                [
                    535.8636363636363,
                    447.2272727272727
                ]
            ],
            "group_id": null,
            "description": "",
            "shape_type": "rectangle",
            "flags": {},
            "mask": null
        },
        {
            "label": "1",
            "points": [
                [
                    457.83333333333337,
                    408.42857142857144
                ],
                [
                    611.4047619047619,
                    539.3809523809524
                ]
            ],
            "group_id": null,
            "description": "",
            "shape_type": "rectangle",
            "flags": {},
            "mask": null
        },
        {
            "label": "1",
            "points": [
                [
                    603.0714285714286,
                    666.7619047619048
                ],
                [
                    510.21428571428567,
                    579.8571428571429
                ]
            ],
            "group_id": null,
            "description": "",
            "shape_type": "rectangle",
            "flags": {},
            "mask": null
        },
        {
            "label": "1",
            "points": [
                [
                    295.92857142857144,
                    908.4285714285714
                ],
                [
                    331.6428571428571,
                    951.2857142857143
                ]
            ],
            "group_id": null,
            "description": "",
            "shape_type": "rectangle",
            "flags": {},
            "mask": null
        }
    ],
    "imageHeight": 1024,
    "imageWidth": 1024
}