{
    "version": "5.4.1",
    "flags": {},
    "shapes": [
        {
            "label": "1",
            "points": [
                [
                    7.103092783505161,
                    786.4845360824743
                ],
                [
                    108.13402061855672,
                    889.0618556701031
                ]
            ],
            "group_id": null,
            "description": "",
            "shape_type": "rectangle",
            "flags": {},
            "mask": null
        },
        {
            "label": "1",
            "points": [
                [
                    93.70103092783503,
                    659.1649484536083
                ],
                [
                    194.7319587628866,
                    742.1546391752578
                ]
            ],
            "group_id": null,
            "description": "",
            "shape_type": "rectangle",
            "flags": {},
            "mask": null
        },
        {
            "label": "1",
            "points": [
                [
                    443.70103092783506,
                    312.7731958762887
                ],
                [
                    553.4948453608248,
                    401.94845360824746
                ]
            ],
            "group_id": null,
            "description": "",
            "shape_type": "rectangle",
            "flags": {},
            "mask": null
        }
    ],
    "imageHeight": 1024,
    "imageWidth": 1024
}