{
    "version": "5.4.1",
    "flags": {},
    "shapes": [
        {
            "label": "1",
            "points": [
                [
                    724.5000000000001,
                    179.85714285714283
                ],
                [
                    767.3571428571428,
                    212.0
                ]
            ],
            "group_id": null,
            "description": "",
            "shape_type": "rectangle",
            "flags": {},
            "mask": null
        },
        {
            "label": "1",
            "points": [
                [
                    719.7380952380953,
                    246.52380952380952
                ],
                [
                    792.3571428571428,
                    315.5714285714286
                ]
            ],
            "group_id": null,
            "description": "",
            "shape_type": "rectangle",
            "flags": {},
            "mask": null
        }
    ],
    "imageHeight": 1024,
    "imageWidth": 1024
}