{
    "version": "5.4.1",
    "flags": {},
    "shapes": [
        {
            "label": "1",
            "points": [
                [
                    481.6428571428571,
                    429.8571428571429
                ],
                [
                    674.5000000000001,
                    587.0
                ]
            ],
            "group_id": null,
            "description": "",
            "shape_type": "rectangle",
            "flags": {},
            "mask": null
        },
        {
            "label": "1",
            "points": [
                [
                    536.4047619047619,
                    279.8571428571429
                ],
                [
                    638.7857142857143,
                    414.3809523809524
                ]
            ],
            "group_id": null,
            "description": "",
            "shape_type": "rectangle",
            "flags": {},
            "mask": null
        }
    ],
    "imageHeight": 1024,
    "imageWidth": 1024
}