{
    "version": "5.4.1",
    "flags": {},
    "shapes": [
        {
            "label": "1",
            "points": [
                [
                    142.3571428571429,
                    423.9047619047619
                ],
                [
                    237.59523809523807,
                    531.047619047619
                ]
            ],
            "group_id": null,
            "description": "",
            "shape_type": "rectangle",
            "flags": {},
            "mask": null
        }
    ],
    "imageHeight": 1024,
    "imageWidth": 1024
}