{
    "version": "5.4.1",
    "flags": {},
    "shapes": [
        {
            "label": "1",
            "points": [
                [
                    541.639175257732,
                    526.1752577319588
                ],
                [
                    767.4123711340206,
                    767.4123711340206
                ]
            ],
            "group_id": null,
            "description": "",
            "shape_type": "rectangle",
            "flags": {},
            "mask": null
        },
        {
            "label": "1",
            "points": [
                [
                    626.1752577319588,
                    323.08247422680415
                ],
                [
                    739.577319587629,
                    540.6082474226804
                ]
            ],
            "group_id": null,
            "description": "",
            "shape_type": "rectangle",
            "flags": {},
            "mask": null
        },
        {
            "label": "1",
            "points": [
                [
                    723.0824742268042,
                    274.62886597938143
                ],
                [
                    800.4020618556701,
                    332.87628865979383
                ]
            ],
            "group_id": null,
            "description": "",
            "shape_type": "rectangle",
            "flags": {},
            "mask": null
        },
        {
            "label": "1",
            "points": [
                [
                    856.0721649484537,
                    151.9484536082474
                ],
                [
                    1023.0,
                    308.1888358058838
                ]
            ],
            "group_id": null,
            "description": "",
            "shape_type": "rectangle",
            "flags": {},
            "mask": null
        },
        {
            "label": "1",
            "points": [
                [
                    979.7835051546392,
                    427.2061855670103
                ],
                [
                    1023.0,
                    522.2824742268042
                ]
            ],
            "group_id": null,
            "description": "",
            "shape_type": "rectangle",
            "flags": {},
            "mask": null
        }
    ],
    "imageHeight": 1024,
    "imageWidth": 1024
}