{
    "version": "5.4.1",
    "flags": {},
    "shapes": [
        {
            "label": "1",
            "points": [
                [
                    208.9072164948454,
                    261.74226804123714
                ],
                [
                    371.7938144329897,
                    388.54639175257734
                ]
            ],
            "group_id": null,
            "description": "",
            "shape_type": "rectangle",
            "flags": {},
            "mask": null
        },
        {
            "label": "1",
            "points": [
                [
                    290.8659793814433,
                    399.88659793814435
                ],
                [
                    339.83505154639175,
                    437.0
                ]
            ],
            "group_id": null,
            "description": "",
            "shape_type": "rectangle",
            "flags": {},
            "mask": null
        },
        {
            "label": "1",
            "points": [
                [
                    377.4639175257732,
                    380.29896907216494
                ],
                [
                    434.16494845360825,
                    438.54639175257734
                ]
            ],
            "group_id": null,
            "description": "",
            "shape_type": "rectangle",
            "flags": {},
            "mask": null
        },
        {
            "label": "1",
            "points": [
                [
                    351.6907216494845,
                    433.9072164948454
                ],
                [
                    404.78350515463916,
                    478.75257731958766
                ]
            ],
            "group_id": null,
            "description": "",
            "shape_type": "rectangle",
            "flags": {},
            "mask": null
        },
        {
            "label": "1",
            "points": [
                [
                    409.93814432989694,
                    397.82474226804123
                ],
                [
                    619.7319587628865,
                    535.4536082474227
                ]
            ],
            "group_id": null,
            "description": "",
            "shape_type": "rectangle",
            "flags": {},
            "mask": null
        },
        {
            "label": "1",
            "points": [
                [
                    273.8556701030928,
                    639.5773195876288
                ],
                [
                    508.9072164948454,
                    762.7731958762887
                ]
            ],
            "group_id": null,
            "description": "",
            "shape_type": "rectangle",
            "flags": {},
            "mask": null
        }
    ],
    "imageHeight": 1024,
    "imageWidth": 1024
}