{
    "version": "5.4.1",
    "flags": {},
    "shapes": [
        {
            "label": "1",
            "points": [
                [
                    99.39837398373982,
                    571.349593495935
                ],
                [
                    306.7154471544715,
                    726.6341463414634
                ]
            ],
            "group_id": null,
            "description": "",
            "shape_type": "rectangle",
            "flags": {},
            "mask": null
        },
        {
            "label": "1",
            "points": [
                [
                    542.4878048780488,
                    603.0569105691058
                ],
                [
                    601.8373983739837,
                    656.7154471544716
                ]
            ],
            "group_id": null,
            "description": "",
            "shape_type": "rectangle",
            "flags": {},
            "mask": null
        }
    ],
    "imageHeight": 1024,
    "imageWidth": 1024
}