{
    "version": "5.4.1",
    "flags": {},
    "shapes": [
        {
            "label": "1",
            "points": [
                [
                    628.0714285714286,
                    279.8571428571429
                ],
                [
                    544.1428571428571,
                    371.5238095238095
                ]
            ],
            "group_id": null,
            "description": "",
            "shape_type": "rectangle",
            "flags": {},
            "mask": null
        },
        {
            "label": "1",
            "points": [
                [
                    395.3333333333333,
                    616.7619047619048
                ],
                [
                    316.16666666666663,
                    541.7619047619048
                ]
            ],
            "group_id": null,
            "description": "",
            "shape_type": "rectangle",
            "flags": {},
            "mask": null
        },
        {
            "label": "1",
            "points": [
                [
                    360.21428571428567,
                    542.952380952381
                ],
                [
                    243.54761904761904,
                    402.4761904761905
                ]
            ],
            "group_id": null,
            "description": "",
            "shape_type": "rectangle",
            "flags": {},
            "mask": null
        }
    ],
    "imageHeight": 1024,
    "imageWidth": 1024
}