{
    "version": "5.4.1",
    "flags": {},
    "shapes": [
        {
            "label": "1",
            "points": [
                [
                    581.5384615384615,
                    477.30769230769226
                ],
                [
                    610.3846153846154,
                    533.4615384615385
                ]
            ],
            "group_id": null,
            "description": "",
            "shape_type": "rectangle",
            "flags": {},
            "mask": null
        },
        {
            "label": "n",
            "points": [
                [
                    582.3076923076923,
                    435.0
                ],
                [
                    628.4615384615385,
                    468.46153846153845
                ]
            ],
            "group_id": null,
            "description": "",
            "shape_type": "rectangle",
            "flags": {},
            "mask": null
        },
        {
            "label": "n",
            "points": [
                [
                    553.0769230769231,
                    455.38461538461536
                ],
                [
                    568.4615384615385,
                    478.8461538461538
                ]
            ],
            "group_id": null,
            "description": "",
            "shape_type": "rectangle",
            "flags": {},
            "mask": null
        }
    ],
    "imageHeight": 1024,
    "imageWidth": 1024
}