{
    "version": "5.4.1",
    "flags": {},
    "shapes": [
        {
            "label": "1",
            "points": [
                [
                    382.83333333333337,
                    446.5238095238095
                ],
                [
                    625.6904761904761,
                    595.3333333333334
                ]
            ],
            "group_id": null,
            "description": "",
            "shape_type": "rectangle",
            "flags": {},
            "mask": null
        },
        {
            "label": "1",
            "points": [
                [
                    272.7142857142857,
                    556.047619047619
                ],
                [
                    346.5238095238096,
                    754.8571428571429
                ]
            ],
            "group_id": null,
            "description": "",
            "shape_type": "rectangle",
            "flags": {},
            "mask": null
        },
        {
            "label": "1",
            "points": [
                [
                    198.90476190476187,
                    615.5714285714286
                ],
                [
                    0.0,
                    421.5238095238095
                ]
            ],
            "group_id": null,
            "description": "",
            "shape_type": "rectangle",
            "flags": {},
            "mask": null
        },
        {
            "label": "1",
            "points": [
                [
                    738.1904761904761,
                    212.0
                ],
                [
                    997.0413049197579,
                    0.0
                ]
            ],
            "group_id": null,
            "description": "",
            "shape_type": "rectangle",
            "flags": {},
            "mask": null
        },
        {
            "label": "1",
            "points": [
                [
                    617.952380952381,
                    827.4761904761905
                ],
                [
                    789.3809523809523,
                    977.4761904761905
                ]
            ],
            "group_id": null,
            "description": "",
            "shape_type": "rectangle",
            "flags": {},
            "mask": null
        },
        {
            "label": "1",
            "points": [
                [
                    769.7380952380953,
                    341.76190476190476
                ],
                [
                    667.3571428571429,
                    496.5238095238095
                ]
            ],
            "group_id": null,
            "description": "",
            "shape_type": "rectangle",
            "flags": {},
            "mask": null
        }
    ],
    "imageHeight": 1024,
    "imageWidth": 1024
}